{
  "adv-injection-checks": "pending",
  "amass": "done",
  "assetfinder": "pending",
  "cewl": "pending",
  "clickjacking-checks": "pending",
  "consolidate": "done",
  "cors-checks": "pending",
  "csrf-checks": "pending",
  "ctl": "pending",
  "dnsx-validate": "pending",
  "dork-links": "done",
  "fuzz-dirs": "pending",
  "fuzz-docs": "done",
  "gau": "pending",
  "httpx": "done",
  "injection-checks": "pending",
  "katana": "pending",
  "load-config": "done",
  "nmap-enrichment-checks": "pending",
  "open-redirect-checks": "pending",
  "param-fuzz": "pending",
  "robots-sitemaps": "pending",
  "server-input-checks": "pending",
  "smuggling-stack-checks": "pending",
  "subfinder": "pending",
  "sublist3r": "done",
  "tier-isolation-checks": "pending",
  "url-corpus": "pending",
  "validate-inputs": "done",
  "waybackurls": "pending",
  "workflow-logic-checks": "pending"
}